zeit/msal/__init__.py
zeit/msal/authenticate.py
zeit/msal/cache.py
zeit/msal/cli.py
zeit_msal-1.3.1.dist-info/METADATA
zeit_msal-1.3.1.dist-info/WHEEL
zeit_msal-1.3.1.dist-info/entry_points.txt
zeit_msal-1.3.1.dist-info/licenses/LICENSE
zeit_msal-1.3.1.dist-info/RECORD
