Metadata-Version: 2.4
Name: zeit.msal
Version: 1.3.1
Summary: Microsoft Azure AD authentication helper for CLI applications
Project-URL: Repository, https://github.com/ZeitOnline/zeit.msal
Author-email: Zeit Online <zon-backend@zeit.de>
License-File: LICENSE
Requires-Dist: click
Requires-Dist: msal
